upstox_api/__init__.py
upstox_api/api.py
upstox_api/service_config.json
upstox_api/utils.py
upstox_api/constants/__init__.py
upstox_api/constants/exchanges.py
upstox_api/constants/misc.py
upstox-2.0.1.dist-info/LICENSE
upstox-2.0.1.dist-info/METADATA
upstox-2.0.1.dist-info/WHEEL
upstox-2.0.1.dist-info/top_level.txt
upstox-2.0.1.dist-info/RECORD
