Metadata-Version: 1.1
Name: upstox
Version: 2.0.1
Summary: Official Python library for Upstox APIs
Home-page: https://github.com/upstox/upstox-python
Author: Upstox Development Team
Author-email: support@upstox.com
License: UNKNOWN
Keywords: upstox,python,sdk,trading,stock markets
Platform: UNKNOWN
Classifier: Intended Audience :: Developers
Classifier: Natural Language :: English
Classifier: Operating System :: OS Independent
Classifier: Programming Language :: Python
Classifier: Programming Language :: Python :: 2
Classifier: Programming Language :: Python :: 3
Classifier: Programming Language :: Python :: Implementation :: PyPy
Classifier: Topic :: Software Development :: Libraries :: Python Modules
